dew_ws_tools/__init__.py
dew_ws_tools/publish_locally.py
dew_ws_tools-0.12.dist-info/LICENSE
dew_ws_tools-0.12.dist-info/METADATA
dew_ws_tools-0.12.dist-info/WHEEL
dew_ws_tools-0.12.dist-info/entry_points.txt
dew_ws_tools-0.12.dist-info/top_level.txt
dew_ws_tools-0.12.dist-info/RECORD
