Metadata-Version: 2.1
Name: dew_ws_tools
Version: 0.12
Summary: Manage internal Python tools for DEW Water Science
Home-page: https://github.com/dew-waterscience/dew_ws_tools
Requires-Python: >=3.8
License-File: LICENSE
Requires-Dist: loguru
Requires-Dist: pydata-sphinx-theme
